pytulpa/__init__.py
pytulpa/activations.py
pytulpa/core.py
pytulpa/layers.py
pytulpa/models.py
pytulpa/optimizers.py
pytulpa-0.1.0.dist-info/LICENSE
pytulpa-0.1.0.dist-info/METADATA
pytulpa-0.1.0.dist-info/WHEEL
pytulpa-0.1.0.dist-info/top_level.txt
pytulpa-0.1.0.dist-info/RECORD
